giphy_test_ti_client/__init__.py
giphy_test_ti_client/api_client.py
giphy_test_ti_client/api_response.py
giphy_test_ti_client/configuration.py
giphy_test_ti_client/exceptions.py
giphy_test_ti_client/py.typed
giphy_test_ti_client/rest.py
giphy_test_ti_client/api/__init__.py
giphy_test_ti_client/api/gifs_api.py
giphy_test_ti_client/api/stickers_api.py
giphy_test_ti_client/models/__init__.py
giphy_test_ti_client/models/get_gifs_by_id200_response.py
giphy_test_ti_client/models/gif.py
giphy_test_ti_client/models/gif_images.py
giphy_test_ti_client/models/gif_images_downsized.py
giphy_test_ti_client/models/gif_images_downsized_large.py
giphy_test_ti_client/models/gif_images_downsized_medium.py
giphy_test_ti_client/models/gif_images_downsized_small.py
giphy_test_ti_client/models/gif_images_downsized_still.py
giphy_test_ti_client/models/gif_images_fixed_height.py
giphy_test_ti_client/models/gif_images_fixed_height_downsampled.py
giphy_test_ti_client/models/gif_images_fixed_height_small.py
giphy_test_ti_client/models/gif_images_fixed_height_small_still.py
giphy_test_ti_client/models/gif_images_fixed_height_still.py
giphy_test_ti_client/models/gif_images_fixed_width.py
giphy_test_ti_client/models/gif_images_fixed_width_downsampled.py
giphy_test_ti_client/models/gif_images_fixed_width_small.py
giphy_test_ti_client/models/gif_images_fixed_width_small_still.py
giphy_test_ti_client/models/gif_images_fixed_width_still.py
giphy_test_ti_client/models/gif_images_looping.py
giphy_test_ti_client/models/gif_images_original.py
giphy_test_ti_client/models/gif_images_original_still.py
giphy_test_ti_client/models/gif_images_preview.py
giphy_test_ti_client/models/gif_images_preview_gif.py
giphy_test_ti_client/models/image.py
giphy_test_ti_client/models/meta.py
giphy_test_ti_client/models/pagination.py
giphy_test_ti_client/models/random_gif200_response.py
giphy_test_ti_client/models/user.py
giphy_test_ti_client-1.0.0.dist-info/METADATA
giphy_test_ti_client-1.0.0.dist-info/WHEEL
giphy_test_ti_client-1.0.0.dist-info/top_level.txt
giphy_test_ti_client-1.0.0.dist-info/RECORD
